{
  "head0": {
    "type": "header",
    "description": "Settings for cryptocoins@pbojan"
  },

  "head1" : {
    "type" : "header",
    "description" : "Coin Options"
  },

  "coin": {
    "type": "combobox",
    "default": "bitcoin",
    "description": "Select Coin",
    "tooltip": "For which coin to show information on the ticker",
    "options": {
      "Bitcoin": "bitcoin",
      "Ethereum": "ethereum",
      "Bitcoin Cash": "bitcoin-cash",
      "Litecoin": "litecoin",
      "Ripple": "ripple",
      "0x": "0x",
      "Achain": "achain",
      "Aeternity": "aeternity",
      "Aion": "aion",
      "Ardor": "ardor",
      "Ark": "ark",
      "Augur": "augur",
      "Bancor": "bancor",
      "Basic Attention Token": "basic-attention-token",
      "Binance Coin": "binance-coin",
      "BitConnect": "bitconnect",
      "BitShares": "bitshares",
      "Bitcoin Gold": "bitcoin-gold",
      "BitcoinDark": "bitcoindark",
      "Blocknet": "blocknet",
      "Byteball Bytes": "byteball",
      "Bytecoin": "bytecoin-bcn",
      "Bytom": "bytom",
      "Cardano": "cardano",
      "Civic": "civic",
      "Dash": "dash",
      "Decentraland": "decentraland",
      "Decred": "decred",
      "DigiByte": "digibyte",
      "DigixDAO": "digixdao",
      "Dogecoin": "dogecoin",
      "Dragonchain": "dragonchain",
      "EOS": "eos",
      "Edgeless": "edgeless",
      "Einsteinium": "einsteinium",
      "Ethereum Classic": "ethereum-classic",
      "Ethos": "ethos",
      "Exchange Union": "exchange-union",
      "Factom": "factom",
      "FunFair": "funfair",
      "GXShares": "gxshares",
      "GameCredits": "gamecredits",
      "Gnosis": "gnosis-gno",
      "Golem": "golem-network-tokens",
      "GridCoin": "gridcoin",
      "Hshare": "hshare",
      "IOTA": "iota",
      "Iconomi": "iconomi",
      "Komodo": "komodo",
      "Kyber Network": "kyber-network",
      "Lisk": "lisk",
      "MaidSafeCoin": "maidsafecoin",
      "Metal": "metal",
      "Metaverse ETP": "metaverse",
      "MinexCoin": "minexcoin",
      "MonaCoin": "monacoin",
      "Monaco": "monaco",
      "Monero": "monero",
      "Nano": "nano",
      "NAV Coin": "nav-coin",
      "NEM": "nem",
      "NEO": "neo",
      "Nxt": "nxt",
      "OmiseGO": "omisego",
      "PIVX": "pivx",
      "Populous": "populous",
      "Pura": "pura",
      "QASH": "qash",
      "Qtum": "qtum",
      "RChain": "rchain",
      "Raiden Network Token": "raiden-network-token",
      "SALT": "salt",
      "Santiment Network Token": "santiment",
      "Siacoin": "siacoin",
      "Skycoin": "skycoin",
      "Status": "status",
      "Steem": "steem",
      "Stellar Lumens": "stellar",
      "Storj": "storj",
      "Stratis": "stratis",
      "Streamr DATAcoin": "streamr-datacoin",
      "TRON": "tron",
      "TenX": "tenx",
      "Tether": "tether",
      "VeChain": "vechain",
      "Verge": "verge",
      "Veritaseum": "veritaseum",
      "Vertcoin": "vertcoin",
      "Walton": "walton",
      "Waves": "waves",
      "ZCoin": "zcoin",
      "Zcash": "zcash"
    }
  },

  "currency": {
    "type": "combobox",
    "default": "usd",
    "description": "Select Currency",
    "tooltip": "In which currency to show information on the ticker",
    "options": {
      "USD ($)": "usd",
      "EUR (€)": "eur"
    }
  },

  "refreshInterval": {
    "type": "combobox",
    "default": 10,
    "description": "Select Refresh Interval",
    "tooltip": "How often to fetch new data for the ticker",
    "options": {
      "5 Minutes": 5,
      "10 Minutes": 10,
      "15 Minutes": 15,
      "20 Minutes": 20,
      "25 Minutes": 25,
      "30 Minutes": 30,
      "35 Minutes": 35,
      "40 Minutes": 40,
      "45 Minutes": 45,
      "50 Minutes": 50,
      "55 Minutes": 55,
      "1 Hour": 60,
      "2 Hours": 120,
      "4 Hours": 240
    }
  }
}
